{
  "version": "2.0.25",
  "buildDate": "2026-03-31",
  "files": [
    {
      "file": "bitwrench-bccl.cjs.js",
      "format": "CJS",
      "ver": "2.x",
      "component": "bccl",
      "minified": false,
      "raw": 120297,
      "gzipped": 25619,
      "sourceMap": true,
      "integrity": "sha384-RA66j3cZJmQZMYv4wHTmYJFMZHnCCQw1Zn8UcAia7WI4NmGZA3RxLMCHg5IcpQSy"
    },
    {
      "file": "bitwrench-code-edit.cjs.js",
      "format": "CJS",
      "ver": "2.x",
      "component": "code-edit",
      "minified": false,
      "raw": 23549,
      "gzipped": 6084,
      "sourceMap": true,
      "integrity": "sha384-qhWEjthIXdWPGKz1CULfIbI4hv8m/n5ys7kXE0fIQYf4jsYCC1L4GukM5KRqRToS"
    },
    {
      "file": "bitwrench-lean.cjs.js",
      "format": "CJS",
      "ver": "2.x",
      "component": "lean",
      "minified": false,
      "raw": 263621,
      "gzipped": 64767,
      "sourceMap": true,
      "integrity": "sha384-g/xiDIMH6SyLwVQZ4kBw7vd5mwItjwsFm7tt7lagmMPv1GLeq7TRnysAF7NYu1D/"
    },
    {
      "file": "bitwrench-util-css.cjs.js",
      "format": "CJS",
      "ver": "2.x",
      "component": "core",
      "minified": false,
      "raw": 8098,
      "gzipped": 2622,
      "sourceMap": true,
      "integrity": "sha384-eAabzZqdE8Cxj8XFWjOVQmpflXsxaPqFRMklbljSm8QgIUf03ll12xMNrnRdNQ00"
    },
    {
      "file": "bitwrench.cjs.js",
      "format": "CJS",
      "ver": "2.x",
      "component": "core",
      "minified": false,
      "raw": 381220,
      "gzipped": 89439,
      "sourceMap": true,
      "integrity": "sha384-+6wWDHXlpihbUCMcfyuXx6JQn/xmUYFzsIykalbLVHALcWY/00J0dkE9ghNBwWsg"
    },
    {
      "file": "bwserve.cjs.js",
      "format": "CJS",
      "ver": "2.x",
      "component": "bwserve",
      "minified": false,
      "raw": 40678,
      "gzipped": 11633,
      "sourceMap": true,
      "integrity": "sha384-fs6zRLlgLSMl167JZR29LNzjOcOhNjXtJpfpg8Y2xDRmGMJNKK6fBMfSXxnD58Ed"
    },
    {
      "file": "bitwrench-bccl.cjs.min.js",
      "format": "CJS",
      "ver": "2.x",
      "component": "bccl",
      "minified": true,
      "raw": 37885,
      "gzipped": 10929,
      "sourceMap": true,
      "integrity": "sha384-UVKyX6Ep7ITUok4aQ5SpAo56pr/unOqNX1rg0Nqd5TdFRfS/QLsvdpB5i00k/Lp8"
    },
    {
      "file": "bitwrench-code-edit.cjs.min.js",
      "format": "CJS",
      "ver": "2.x",
      "component": "code-edit",
      "minified": true,
      "raw": 11980,
      "gzipped": 4350,
      "sourceMap": true,
      "integrity": "sha384-HRxcDwX9dGKq0OghPsK8ZLiVEzzw1fiEU46qw8btM5hMqdv4x5EFnfkCWDW5LuV+"
    },
    {
      "file": "bitwrench-lean.cjs.min.js",
      "format": "CJS",
      "ver": "2.x",
      "component": "lean",
      "minified": true,
      "raw": 115027,
      "gzipped": 30793,
      "sourceMap": true,
      "integrity": "sha384-NAu0XZcYl9esPSv9usftOKo0gKP3WFfITkErF4/F/nTeRss5HZEoP24OQTHJ0PIb"
    },
    {
      "file": "bitwrench-util-css.cjs.min.js",
      "format": "CJS",
      "ver": "2.x",
      "component": "core",
      "minified": true,
      "raw": 4113,
      "gzipped": 1659,
      "sourceMap": true,
      "integrity": "sha384-0eZt3OMTcA9V74g6Fo/udBm9jFTTT5/cHIa8UQ47z65hJKVpskOr95+l6La8VhxM"
    },
    {
      "file": "bitwrench.cjs.min.js",
      "format": "CJS",
      "ver": "2.x",
      "component": "core",
      "minified": true,
      "raw": 151886,
      "gzipped": 40644,
      "sourceMap": true,
      "integrity": "sha384-um4doW2b9QMWnZFNeN75A12u7MgaxXqfTDD8RRY98TY9aB+Pp8wrOwVQSvYVcy8w"
    },
    {
      "file": "bitwrench.css",
      "format": "CSS",
      "ver": "2.x",
      "component": "core",
      "minified": false,
      "raw": 79944,
      "gzipped": 13157,
      "sourceMap": false,
      "integrity": "sha384-y0YMF2B2xZF3TReu5KAuetdM7I/yFjJ7ATB9/pM//70PbXnn9+NBcb4fsb3cS2pe"
    },
    {
      "file": "bitwrench.min.css",
      "format": "CSS",
      "ver": "2.x",
      "component": "core",
      "minified": true,
      "raw": 65338,
      "gzipped": 11993,
      "sourceMap": false,
      "integrity": "sha384-4ymUTaU2kwrsPLCsEGReVJe2rGzsHkNG1BjrHB7EGAOqMK+SgRvaHPoYUFk7tXSE"
    },
    {
      "file": "bitwrench-code-edit.es5.js",
      "format": "ES5 (UMD)",
      "ver": "2.x",
      "component": "code-edit",
      "minified": false,
      "raw": 28274,
      "gzipped": 6438,
      "sourceMap": true,
      "integrity": "sha384-M7p1KKOG1JGQeW0tQglvyTAUpqSLiDVMCr/CHpasi9/fWWukLBipQ/pDFUggtq86"
    },
    {
      "file": "bitwrench-lean.es5.js",
      "format": "ES5 (UMD)",
      "ver": "2.x",
      "component": "lean",
      "minified": false,
      "raw": 303518,
      "gzipped": 68442,
      "sourceMap": true,
      "integrity": "sha384-md3746BNl73qHbL3qxHW9lJkSXxfl0iNtad8+ueyiNMMYmQtwqmgqcr5wv2Ifidh"
    },
    {
      "file": "bitwrench-util-css.es5.js",
      "format": "ES5 (UMD)",
      "ver": "2.x",
      "component": "core",
      "minified": false,
      "raw": 10081,
      "gzipped": 2953,
      "sourceMap": true,
      "integrity": "sha384-lF7JM6zgkGRpiPmHdBG08yUBlJjfGNEb5il9CRAkM4DfFaWcPuhG57K7JIcFsNf4"
    },
    {
      "file": "bitwrench.es5.js",
      "format": "ES5 (UMD)",
      "ver": "2.x",
      "component": "core",
      "minified": false,
      "raw": 451616,
      "gzipped": 96067,
      "sourceMap": true,
      "integrity": "sha384-ydqqwDi8AY8C9Ns7NughmVlzA7ZMpTIyYB+0+ZWghf1j5btx5Y0Rptx4wU7rxYGJ"
    },
    {
      "file": "bitwrench-code-edit.es5.min.js",
      "format": "ES5 (UMD)",
      "ver": "2.x",
      "component": "code-edit",
      "minified": true,
      "raw": 12187,
      "gzipped": 4405,
      "sourceMap": true,
      "integrity": "sha384-SImIBlVcBZ9Ex5jUsWpOAgtIBe+b8lnMGF1Ym8veGeD0VlY51s4i3u42eymJMjM1"
    },
    {
      "file": "bitwrench-lean.es5.min.js",
      "format": "ES5 (UMD)",
      "ver": "2.x",
      "component": "lean",
      "minified": true,
      "raw": 120686,
      "gzipped": 32174,
      "sourceMap": true,
      "integrity": "sha384-6eZcoh9giHgNLfx3dl8L/ZFNUyqYJRbiQtdEi1QPgD38A6Xu6oY/mNEHLgNdxAqY"
    },
    {
      "file": "bitwrench-util-css.es5.min.js",
      "format": "ES5 (UMD)",
      "ver": "2.x",
      "component": "core",
      "minified": true,
      "raw": 4578,
      "gzipped": 1801,
      "sourceMap": true,
      "integrity": "sha384-vPGI+zh9/gE2hyhlN2NeBxZzNpFuMB/CmQABBD8MOgbL5etd3iaq4UYGIjLBesmW"
    },
    {
      "file": "bitwrench.es5.min.js",
      "format": "ES5 (UMD)",
      "ver": "2.x",
      "component": "core",
      "minified": true,
      "raw": 163852,
      "gzipped": 42609,
      "sourceMap": true,
      "integrity": "sha384-LvrzQJLd5klWf3HVzRoDO8UNNSz3FXJ1WYhwdq4rZA70jqCSVH1kr1qOmqsc/dXB"
    },
    {
      "file": "bitwrench-bccl.esm.js",
      "format": "ESM",
      "ver": "2.x",
      "component": "bccl",
      "minified": false,
      "raw": 120217,
      "gzipped": 25603,
      "sourceMap": true,
      "integrity": "sha384-urwgpnwC8IpMjqShHzGgKjBVghNko0neSy1fkECY7MgFU3auHC2Bcn3MoK9E9BGU"
    },
    {
      "file": "bitwrench-code-edit.esm.js",
      "format": "ESM",
      "ver": "2.x",
      "component": "code-edit",
      "minified": false,
      "raw": 23330,
      "gzipped": 6005,
      "sourceMap": true,
      "integrity": "sha384-h0fE0qWyEVmYoOY/nqJX6bfWlKllg1wTyU7E3N2A8820ZICJ2KZPhDRCp7/BTz+o"
    },
    {
      "file": "bitwrench-lean.esm.js",
      "format": "ESM",
      "ver": "2.x",
      "component": "lean",
      "minified": false,
      "raw": 262758,
      "gzipped": 64568,
      "sourceMap": true,
      "integrity": "sha384-6mJxNfGQWSX5wZDHUfDQtoQop5J8r6mVTmpav2ro61Fc8nyPe91Mf06czeSGTzYB"
    },
    {
      "file": "bitwrench-util-css.esm.js",
      "format": "ESM",
      "ver": "2.x",
      "component": "core",
      "minified": false,
      "raw": 7998,
      "gzipped": 2575,
      "sourceMap": true,
      "integrity": "sha384-I/xcJwIp202GKLwIKIUqkiAWkoUQRFn7fNSorTv/DZe6WovBwpzWWAIr3A1o0ine"
    },
    {
      "file": "bitwrench.esm.js",
      "format": "ESM",
      "ver": "2.x",
      "component": "core",
      "minified": false,
      "raw": 381004,
      "gzipped": 89503,
      "sourceMap": true,
      "integrity": "sha384-lPKbGfBkur2VHJ2kzM11S9koP682I6roeITvEmRzm+R1A+YIqpHa3NWSj92p9w9k"
    },
    {
      "file": "bwserve.esm.js",
      "format": "ESM",
      "ver": "2.x",
      "component": "bwserve",
      "minified": false,
      "raw": 40134,
      "gzipped": 11464,
      "sourceMap": true,
      "integrity": "sha384-ZXn4aIBNgPdwr6QaDGqV9WTCqFIAgWgndQpHs6wZbR9WrErO12kifamD3qaZONOb"
    },
    {
      "file": "bitwrench-bccl.esm.min.js",
      "format": "ESM",
      "ver": "2.x",
      "component": "bccl",
      "minified": true,
      "raw": 37860,
      "gzipped": 10922,
      "sourceMap": true,
      "integrity": "sha384-oZNyOQt9pSv6MeG/1EbkcJjZimSHC+ObW3F6wbixFY2n9wgT+4kEjrBHUW7xah21"
    },
    {
      "file": "bitwrench-code-edit.esm.min.js",
      "format": "ESM",
      "ver": "2.x",
      "component": "code-edit",
      "minified": true,
      "raw": 11879,
      "gzipped": 4309,
      "sourceMap": true,
      "integrity": "sha384-HtIhxNiVOUuAm33FYQkXAUJvSz33TqAKD6Uqv1iwyXlEJi1DrNd43glgL2VjNp7G"
    },
    {
      "file": "bitwrench-lean.esm.min.js",
      "format": "ESM",
      "ver": "2.x",
      "component": "lean",
      "minified": true,
      "raw": 114446,
      "gzipped": 30675,
      "sourceMap": true,
      "integrity": "sha384-A6fDCS7onP178iZA98Ioi7WFmgANXK4gD7TGZTX4E/3FINGtgNJifn8ScEunwlKf"
    },
    {
      "file": "bitwrench-util-css.esm.min.js",
      "format": "ESM",
      "ver": "2.x",
      "component": "core",
      "minified": true,
      "raw": 4037,
      "gzipped": 1620,
      "sourceMap": true,
      "integrity": "sha384-uY+4TDPxWPDWlpfnKP/0SYHZRx4XqxjSQPth1iKoG+uJ34UhiYmPu8Da+lDqXXd8"
    },
    {
      "file": "bitwrench.esm.min.js",
      "format": "ESM",
      "ver": "2.x",
      "component": "core",
      "minified": true,
      "raw": 152191,
      "gzipped": 40893,
      "sourceMap": true,
      "integrity": "sha384-JsRZBx7Iu4030QDS+5g9EIx3wHonD3rtvuFElKBCQVXgyKsCHsvuQIFVqnS4dcOb"
    },
    {
      "file": "bitwrench-bccl.umd.js",
      "format": "UMD",
      "ver": "2.x",
      "component": "bccl",
      "minified": false,
      "raw": 128103,
      "gzipped": 26137,
      "sourceMap": true,
      "integrity": "sha384-VGLCy3tnpKpvnjY/RvARW8mVoHZwycIk0fPbgbh//6xXC3rQEs/tntbqnAWw1oTa"
    },
    {
      "file": "bitwrench-code-edit.umd.js",
      "format": "UMD",
      "ver": "2.x",
      "component": "code-edit",
      "minified": false,
      "raw": 25133,
      "gzipped": 6256,
      "sourceMap": true,
      "integrity": "sha384-jlE6Tns6Lr10JEWXHZUks8IyvsBYik0hWFynXOm6LXxE8jXrpPAEuTNTaa9VAOqY"
    },
    {
      "file": "bitwrench-debug.js",
      "format": "UMD",
      "ver": "2.x",
      "component": "debug",
      "minified": false,
      "raw": 9624,
      "gzipped": 2949,
      "sourceMap": true,
      "integrity": "sha384-dFXWL/RA55mOHgt9WtpcN2EUi5FP1NEdOXffQhTMg7HYQLjjDm+vfihwbHne4qpb"
    },
    {
      "file": "bitwrench-lean.umd.js",
      "format": "UMD",
      "ver": "2.x",
      "component": "lean",
      "minified": false,
      "raw": 277760,
      "gzipped": 65902,
      "sourceMap": true,
      "integrity": "sha384-tI59nJNwNFyhZOSX1uoGLVto0WQk0feHQx+GI71ahwyVbxhufS3mqSzXDLg6eCEY"
    },
    {
      "file": "bitwrench-util-css.umd.js",
      "format": "UMD",
      "ver": "2.x",
      "component": "core",
      "minified": false,
      "raw": 8853,
      "gzipped": 2758,
      "sourceMap": true,
      "integrity": "sha384-Dz9fjqZlIpFd68LNP1GQyTXt6VzwIsM19oxf9I8OQz/pqgO5+bvOjPleHnAd6AcG"
    },
    {
      "file": "bitwrench.umd.js",
      "format": "UMD",
      "ver": "2.x",
      "component": "core",
      "minified": false,
      "raw": 402673,
      "gzipped": 90751,
      "sourceMap": true,
      "integrity": "sha384-trTM4NoRCWS6uVju/sVT/+qrQqAWc2ykIiIJ6EgdqKKWMfWLSj7A63egxbuaesZC"
    },
    {
      "file": "bitwrench-bccl.umd.min.js",
      "format": "UMD",
      "ver": "2.x",
      "component": "bccl",
      "minified": true,
      "raw": 38157,
      "gzipped": 10972,
      "sourceMap": true,
      "integrity": "sha384-o2IJV021qMlcfCCogT9BUCq7XGz5GkigYSnQfvybRx6kYNJC8txz5x/v5DjuqUUI"
    },
    {
      "file": "bitwrench-code-edit.umd.min.js",
      "format": "UMD",
      "ver": "2.x",
      "component": "code-edit",
      "minified": true,
      "raw": 12187,
      "gzipped": 4404,
      "sourceMap": true,
      "integrity": "sha384-M6F7F7tqxV8EykfZrRv9bDOYZOwkHw9bH0znMHRnJo6MbwklnrY10rb808z4FcQF"
    },
    {
      "file": "bitwrench-debug.min.js",
      "format": "UMD",
      "ver": "2.x",
      "component": "debug",
      "minified": true,
      "raw": 4272,
      "gzipped": 1740,
      "sourceMap": true,
      "integrity": "sha384-9xekM72GEadAZz/xeh3MmazFmS8lAyXOt9M5fLzjINPaIvk2Tyfr29a9e44GJGci"
    },
    {
      "file": "bitwrench-lean.umd.min.js",
      "format": "UMD",
      "ver": "2.x",
      "component": "lean",
      "minified": true,
      "raw": 115593,
      "gzipped": 30881,
      "sourceMap": true,
      "integrity": "sha384-Lk1yDDqJbSTh3QoWl9t9WQqnOf3RqUdDswVgUPWFHbirBt77ZJF6v/MfT5cwWHFd"
    },
    {
      "file": "bitwrench-util-css.umd.min.js",
      "format": "UMD",
      "ver": "2.x",
      "component": "core",
      "minified": true,
      "raw": 4351,
      "gzipped": 1738,
      "sourceMap": true,
      "integrity": "sha384-RCuWraavRluQ5MEtVYWgtrEzSj8FanNT20plj0aYTP+60IHIlAeULwYYu6UkNt1i"
    },
    {
      "file": "bitwrench.umd.min.js",
      "format": "UMD",
      "ver": "2.x",
      "component": "core",
      "minified": true,
      "raw": 152486,
      "gzipped": 40735,
      "sourceMap": true,
      "integrity": "sha384-uYz9u6YCCcaYyJ5SFjvgLo3j+ThD6WgciFEFtlk6t36dgp2d9rsxvVPG5QTLC8Sy"
    }
  ]
}